pysigrok_wavedrom.py
pysigrok_format_wavedrom-0.0.2.dist-info/entry_points.txt
pysigrok_format_wavedrom-0.0.2.dist-info/LICENSE
pysigrok_format_wavedrom-0.0.2.dist-info/WHEEL
pysigrok_format_wavedrom-0.0.2.dist-info/METADATA
pysigrok_format_wavedrom-0.0.2.dist-info/RECORD
