Metadata-Version: 2.1
Name: pysigrok-format-wavedrom
Version: 0.0.2
Summary: PySigrok driver for wavedrom
Author-email: Scott Shawcroft <scott@tannewt.org>
Requires-Python: >=3.7
Classifier: License :: OSI Approved :: MIT License
Requires-Dist: pysigrok >= 0.4.0
Requires-Dist: pyvcd < 0.4.0
Project-URL: Home, https://github.com/pysigrok/format-wavedrom
